xlscrap/__init__.py
xlscrap-0.1.0.dist-info/LICENSE
xlscrap-0.1.0.dist-info/WHEEL
xlscrap-0.1.0.dist-info/METADATA
xlscrap-0.1.0.dist-info/RECORD
