Metadata-Version: 2.1
Name: xlscrap
Version: 0.1.0
Summary: A package to ease Excel files mass data extraction
License: BSD-3-Clause
Keywords: spreadsheet,poetry
Author: Philippe ENTZMANN
Author-email: philippe@phec.net
Requires-Python: >=3.7,<4.0
Classifier: License :: OSI Approved :: BSD License
Classifier: Programming Language :: Python :: 3
Classifier: Programming Language :: Python :: 3.7
Requires-Dist: openpyxl (>=2.6,<3.0)
